ephem-stubs/METADATA.toml
ephem-stubs/__init__.pyi
ephem-stubs/_libastro.pyi
ephem-stubs/cities.pyi
ephem-stubs/py.typed
ephem-stubs/stars.pyi
types_ephem-4.2.0.20260116.dist-info/licenses/LICENSE
types_ephem-4.2.0.20260116.dist-info/METADATA
types_ephem-4.2.0.20260116.dist-info/WHEEL
types_ephem-4.2.0.20260116.dist-info/top_level.txt
types_ephem-4.2.0.20260116.dist-info/RECORD
